wallpaper_engine_linux/__init__.py
wallpaper_engine_linux/connect.py
wallpaper_engine_linux-0.1.0.dist-info/METADATA
wallpaper_engine_linux-0.1.0.dist-info/WHEEL
wallpaper_engine_linux-0.1.0.dist-info/entry_points.txt
wallpaper_engine_linux-0.1.0.dist-info/RECORD
